{"_type":"export","__export_format":4,"__export_date":"2020-07-21T05:33:28.960Z","__export_source":"insomnia.desktop.app:v2020.3.3","resources":[{"_id":"req_36b6137f91584d52ae4f9b79963e3cd9","authentication":{},"body":{"mimeType":"application/json","text":"{\n\t\"email\": \"email@email.com\",\n\t\"password\": \"123456\"\n}"},"created":1595193872356,"description":"","headers":[{"id":"pair_2ae12d9d2f8f4dce85b7c2ba12170297","name":"Content-Type","value":"application/json"}],"isPrivate":false,"metaSortKey":-1595193872356,"method":"POST","modified":1595306472211,"name":"Create","parameters":[],"parentId":"fld_5ace8d2ccf704f3c98dabaa2338f7f7e","settingDisableRenderRequestBody":false,"settingEncodeUrl":true,"settingFollowRedirects":"global","settingRebuildPath":true,"settingSendCookies":true,"settingStoreCookies":true,"url":"{{ base_URL }}/sessions","_type":"request"},{"_id":"fld_5ace8d2ccf704f3c98dabaa2338f7f7e","created":1595193863644,"description":"","environment":{},"environmentPropertyOrder":null,"metaSortKey":-1595193863644,"modified":1595193863644,"name":"Sessions","parentId":"wrk_5960c1617cc04d8db96087b4ecdeaafb","_type":"request_group"},{"_id":"wrk_5960c1617cc04d8db96087b4ecdeaafb","created":1594267458044,"description":"","modified":1594267496015,"name":"GoBarber 2.0","parentId":null,"scope":null,"_type":"workspace"},{"_id":"req_8bac9ffc956547f5b49803c57e917791","authentication":{"token":"{{ token }}","type":"bearer"},"body":{"mimeType":"multipart/form-data","params":[{"description":"","fileName":"/Users/luizortega/Downloads/MsgPlus_Img0933.png","id":"pair_c4b85e152e2b415d9aab7c681243c0e5","name":"avatar","type":"file","value":""}]},"created":1595218524925,"description":"","headers":[{"id":"pair_c095b4d8b2bc40d7b1941e19b0b95f19","name":"Content-Type","value":"multipart/form-data"}],"isPrivate":false,"metaSortKey":-1595218524925,"method":"PATCH","modified":1595306772908,"name":"Update Avatar","parameters":[],"parentId":"fld_a930d7caf250477bbfcaee8406964bb1","settingDisableRenderRequestBody":false,"settingEncodeUrl":true,"settingFollowRedirects":"global","settingRebuildPath":true,"settingSendCookies":true,"settingStoreCookies":true,"url":"{{ base_URL }}/users/avatar","_type":"request"},{"_id":"fld_a930d7caf250477bbfcaee8406964bb1","created":1595117783549,"description":"","environment":{},"environmentPropertyOrder":null,"metaSortKey":-1595117783549,"modified":1595117783549,"name":"Users","parentId":"wrk_5960c1617cc04d8db96087b4ecdeaafb","_type":"request_group"},{"_id":"req_f4960eeaa36b4e0a90f71cb6df06f021","authentication":{},"body":{"mimeType":"application/json","text":"{\n\t\"name\": \"Luiz Ortega\",\n\t\"email\": \"email@email.com\",\n\t\"password\": \"123456\"\n}"},"created":1595117791435,"description":"","headers":[{"id":"pair_e02d082368c142959fc999f5c4a6ef6f","name":"Content-Type","value":"application/json"}],"isPrivate":false,"metaSortKey":-1595117791435,"method":"POST","modified":1595305501864,"name":"Create","parameters":[],"parentId":"fld_a930d7caf250477bbfcaee8406964bb1","settingDisableRenderRequestBody":false,"settingEncodeUrl":true,"settingFollowRedirects":"global","settingRebuildPath":true,"settingSendCookies":true,"settingStoreCookies":true,"url":"{{ base_URL }}/users","_type":"request"},{"_id":"req_ed721a1582a645eb845af68211bde534","authentication":{"token":"{{ token }}","type":"bearer"},"body":{"mimeType":"application/json","text":"{\n\t\"provider\": \"Evandro\",\n\t\"date\": \"{% now 'iso-8601', '' %}\"\n}"},"created":1594267519434,"description":"","headers":[{"id":"pair_c181f518251f423986ca80c7ea41c085","name":"Content-Type","value":"application/json"}],"isPrivate":false,"metaSortKey":-1594267519434,"method":"GET","modified":1595196315831,"name":"List","parameters":[],"parentId":"fld_b333e4bb6db84e58818ab1bef7dd8761","settingDisableRenderRequestBody":false,"settingEncodeUrl":true,"settingFollowRedirects":"global","settingRebuildPath":true,"settingSendCookies":true,"settingStoreCookies":true,"url":"{{ base_URL  }}/appointments","_type":"request"},{"_id":"fld_b333e4bb6db84e58818ab1bef7dd8761","created":1594267505812,"description":"","environment":{},"environmentPropertyOrder":null,"metaSortKey":-1594267505812,"modified":1594267505812,"name":"Appointments","parentId":"wrk_5960c1617cc04d8db96087b4ecdeaafb","_type":"request_group"},{"_id":"req_44e369523ed241ef9088b8298692822a","authentication":{"token":"{{ token }}","type":"bearer"},"body":{"mimeType":"application/json","text":"{\n\t\"provider_id\": \"c8ec17cf-2a33-4890-b548-4ab527658277\",\n\t\"date\": \"{% now 'iso-8601', '' %}\"\n}"},"created":1594588446810,"description":"","headers":[{"id":"pair_c181f518251f423986ca80c7ea41c085","name":"Content-Type","value":"application/json"}],"isPrivate":false,"metaSortKey":-1594135015080,"method":"POST","modified":1595196390478,"name":"Create","parameters":[],"parentId":"fld_b333e4bb6db84e58818ab1bef7dd8761","settingDisableRenderRequestBody":false,"settingEncodeUrl":true,"settingFollowRedirects":"global","settingRebuildPath":true,"settingSendCookies":true,"settingStoreCookies":true,"url":"{{ base_URL  }}/appointments","_type":"request"},{"_id":"env_3e0a8941e725b6f9a88065bca1ceb4adfe1e7b66","color":null,"created":1594267458220,"data":{},"dataPropertyOrder":null,"isPrivate":false,"metaSortKey":1594267458220,"modified":1594267458220,"name":"Base Environment","parentId":"wrk_5960c1617cc04d8db96087b4ecdeaafb","_type":"environment"},{"_id":"jar_3e0a8941e725b6f9a88065bca1ceb4adfe1e7b66","cookies":[],"created":1594267458221,"modified":1594267458221,"name":"Default Jar","parentId":"wrk_5960c1617cc04d8db96087b4ecdeaafb","_type":"cookie_jar"},{"_id":"spc_adede3a5e1a141c08a9ecf0c501c80d7","contentType":"yaml","contents":"","created":1594267458048,"fileName":"GoBarber","modified":1594267458048,"parentId":"wrk_5960c1617cc04d8db96087b4ecdeaafb","_type":"api_spec"},{"_id":"env_0e5bc3973b31494891108236e1d687d9","color":"#7751cc","created":1594267532853,"data":{"base_URL":"http://localhost:3333","token":"eyJhbGciOiJIUzI1NiIsInR5cCI6IkpXVCJ9.eyJpYXQiOjE1OTUzMDY0NzUsImV4cCI6MTU5NTM5Mjg3NSwic3ViIjoiY2ZiZjgyY2UtNTQ4My00ZDgyLThjMzgtNDM4NWEzZjE5NDRhIn0.VEfUMM6s8B1Uh5HhMNzoHKuXRBcewbRgxeYcJeFRF5w"},"dataPropertyOrder":{"&":["base_URL","token"]},"isPrivate":false,"metaSortKey":1594267532853,"modified":1595306506292,"name":"dev","parentId":"env_3e0a8941e725b6f9a88065bca1ceb4adfe1e7b66","_type":"environment"}]}